libproshade.dylib
proshade.so
proshade/CMakeLists.txt
proshade/Doxyfile
proshade/LICENSE.txt
proshade/Logo_small.png
proshade/ToDo.txt
proshade/error_list.txt
proshade/standardDependencies.txt
proshade/cmake/bin/CMakeLists.txt
proshade/cmake/bin/bin.cmake
proshade/cmake/checkTypeSizes/CheckTypeSize.c.in
proshade/cmake/checkTypeSizes/CheckTypeSize.cmake
proshade/cmake/findFFTW/FindFFTW.cmake
proshade/cmake/findLapack/CMakePushCheckState.cmake
proshade/cmake/findLapack/CheckFunctionExists.cmake
proshade/cmake/findLapack/Findlapack.cmake
proshade/cmake/lib/CMakeLists.txt
proshade/cmake/lib/lib.cmake
proshade/cmake/python/CMakeLists.txt
proshade/cmake/sources/CMakeLists.txt
proshade/documentation/ProSHADE_3JA7.jpg
proshade/documentation/ProSHADE_dists.png
proshade/documentation/ProSHADE_overlay.jpg
proshade/documentation/ProSHADE_rebox.png
proshade/documentation/html/Logo_small.png
proshade/documentation/html/ProSHADE_3JA7.jpg
proshade/documentation/html/ProSHADE_dists.png
proshade/documentation/html/ProSHADE_overlay.jpg
proshade/documentation/html/ProSHADE_rebox.png
proshade/documentation/html/_pro_s_h_a_d_e_8cpp.html
proshade/documentation/html/_pro_s_h_a_d_e_8cpp.js
proshade/documentation/html/_pro_s_h_a_d_e_8cpp_source.html
proshade/documentation/html/_pro_s_h_a_d_e_8hpp.html
proshade/documentation/html/_pro_s_h_a_d_e_8hpp.js
proshade/documentation/html/_pro_s_h_a_d_e_8hpp_source.html
proshade/documentation/html/_pro_s_h_a_d_e__data_8cpp.html
proshade/documentation/html/_pro_s_h_a_d_e__data_8cpp.js
proshade/documentation/html/_pro_s_h_a_d_e__data_8cpp_source.html
proshade/documentation/html/_pro_s_h_a_d_e__data_8hpp.html
proshade/documentation/html/_pro_s_h_a_d_e__data_8hpp.js
proshade/documentation/html/_pro_s_h_a_d_e__data_8hpp_source.html
proshade/documentation/html/_pro_s_h_a_d_e__distances_8cpp.html
proshade/documentation/html/_pro_s_h_a_d_e__distances_8cpp_source.html
proshade/documentation/html/_pro_s_h_a_d_e__distances_8hpp.html
proshade-0.7.6.1.dist-info/METADATA
proshade-0.7.6.1.dist-info/WHEEL
proshade-0.7.6.1.dist-info/top_level.txt
proshade-0.7.6.1.dist-info/RECORD
