Metadata-Version: 2.1
Name: proshade
Version: 0.7.6.1
Summary: Protein Shape Description and Symmetry Detection (ProSHADE) python module
Home-page: https://github.com/michaltykac/proshade
Author: Michal Tykac, Garib N. Murshudov
Author-email: Michal.Tykac@gmail.com
License: UNKNOWN
Download-URL: https://github.com/michaltykac/proshade/archive/v0.7.6.1.tar.gz
Project-URL: Github, https://github.com/michaltykac/proshade
Project-URL: Bug Reports, https://github.com/michaltykac/proshade/issues
Keywords: bioinformatics protein-shapes symmetry-detection computational-biology structural-biology
Platform: Windows10
Platform: Linux
Platform: MacOS
Classifier: Development Status :: 3 - Alpha
Classifier: Intended Audience :: Science/Research
Classifier: License :: OSI Approved :: GNU General Public License (GPL)
Classifier: Operating System :: POSIX :: Linux
Classifier: Operating System :: MacOS
Classifier: Operating System :: Microsoft :: Windows :: Windows 10
Classifier: Programming Language :: C
Classifier: Programming Language :: C++
Classifier: Programming Language :: Python
Classifier: Topic :: Scientific/Engineering :: Bio-Informatics
